{"version":1,"resource":"vscode-remote://dlytica-academy-work-vm.eastus.cloudapp.azure.com:31997/home/jovyan/Internal/models/silver/college_leads.sql","entries":[{"id":"2Njv.sql","source":"undoRedo.source","timestamp":1734441692991},{"id":"WpZa.sql","timestamp":1734441706116},{"id":"maL1.sql","timestamp":1734441744067},{"id":"dC4q.sql","source":"undoRedo.source","timestamp":1734441751270},{"id":"KdxF.sql","timestamp":1734441763157},{"id":"IAV9.sql","timestamp":1734441941655},{"id":"gby2.sql","timestamp":1734442205104},{"id":"6ED7.sql","timestamp":1734443402678},{"id":"FJuO.sql","source":"undoRedo.source","timestamp":1734443421137},{"id":"rTZO.sql","source":"undoRedo.source","timestamp":1734443560421},{"id":"I8dE.sql","timestamp":1734443616835},{"id":"BwHz.sql","timestamp":1734443937653},{"id":"sR6R.sql","timestamp":1734445791038},{"id":"QCc0.sql","timestamp":1734445810074},{"id":"gfbe.sql","timestamp":1734445834153},{"id":"XUli.sql","timestamp":1734446308097},{"id":"yW0I.sql","timestamp":1734446594547},{"id":"sKP2.sql","timestamp":1734446722747},{"id":"LyQn.sql","source":"undoRedo.source","timestamp":1734446742317},{"id":"Xkf2.sql","timestamp":1734446769193},{"id":"a2z9.sql","timestamp":1734446811775},{"id":"kCFP.sql","timestamp":1734446848567},{"id":"CRiM.sql","timestamp":1734446915154},{"id":"nPFh.sql","timestamp":1734446949360},{"id":"2daf.sql","source":"undoRedo.source","timestamp":1734446953180},{"id":"dLqC.sql","timestamp":1734446963972},{"id":"DWkb.sql","timestamp":1734446986203},{"id":"Fwsh.sql","source":"undoRedo.source","timestamp":1734446994231},{"id":"Of07.sql","timestamp":1734447078074},{"id":"pJwZ.sql","timestamp":1734447108379},{"id":"iuUu.sql","timestamp":1734447128955},{"id":"Oh0G.sql","timestamp":1734447157584},{"id":"dmzW.sql","source":"undoRedo.source","timestamp":1734447163802},{"id":"bgCT.sql","timestamp":1734447177141},{"id":"oPaj.sql","timestamp":1734447187490},{"id":"63xr.sql","timestamp":1734447277426},{"id":"Qvu1.sql","timestamp":1734447445533},{"id":"g09D.sql","timestamp":1734447525642},{"id":"DC9a.sql","timestamp":1734447545866},{"id":"TOhY.sql","source":"undoRedo.source","timestamp":1734447551837},{"id":"Yb1d.sql","timestamp":1734447708994},{"id":"QSg6.sql","timestamp":1734447775375},{"id":"37bz.sql","source":"undoRedo.source","timestamp":1734447792582},{"id":"V41r.sql","timestamp":1734447812526},{"id":"u2at.sql","timestamp":1734448108154},{"id":"XxXk.sql","timestamp":1734453051587},{"id":"cBkZ.sql","timestamp":1734453155504},{"id":"OlEI.sql","source":"undoRedo.source","timestamp":1734453167216},{"id":"3EE0.sql","source":"moved.source","timestamp":1734453393455},{"id":"unIL.sql","timestamp":1734454909153}]}